betterproto_rust_codec-0.1.1.dist-info/METADATA
betterproto_rust_codec-0.1.1.dist-info/WHEEL
betterproto_rust_codec-0.1.1.dist-info/license_files/LICENSE
betterproto_rust_codec/__init__.py
betterproto_rust_codec/__init__.pyi
betterproto_rust_codec/py.typed
betterproto_rust_codec/betterproto_rust_codec.abi3.so
betterproto_rust_codec-0.1.1.dist-info/RECORD
