Metadata-Version: 2.3
Name: betterproto-rust-codec
Version: 0.1.1
Classifier: Programming Language :: Rust
Classifier: Programming Language :: Python :: Implementation :: CPython
Classifier: Programming Language :: Python :: Implementation :: PyPy
License-File: LICENSE
Summary: Fast conversion between betterproto messages and Protobuf wire format.
Author-email: Erik Friese <e.friese0@gmail.com>
License: MIT
Requires-Python: >=3.7
Project-URL: homepage, https://github.com/124C41p/betterproto-rust-codec
Project-URL: repository, https://github.com/124C41p/betterproto-rust-codec
